cc_qa/__init__.py
cc_qa/_constants.py
cc_qa/_version.py
cc_qa/con_checks.py
cc_qa/qcviewer.py
cc_qa/run_qa.py
cc_qa-0.2.1.dist-info/licenses/LICENSE
cc_qa-0.2.1.dist-info/METADATA
cc_qa-0.2.1.dist-info/WHEEL
cc_qa-0.2.1.dist-info/entry_points.txt
cc_qa-0.2.1.dist-info/top_level.txt
cc_qa-0.2.1.dist-info/RECORD
